hive_udf/__init__.py
hive_udf/_make_udf.py
hive_udf/hive_udaf_example.py
hive_udf/hive_udf_args_example.py
hive_udf/hive_udf_example.py
hive_udf/tests.py
hive_udf-1.1.4.dist-info/LICENSE
hive_udf-1.1.4.dist-info/WHEEL
hive_udf-1.1.4.dist-info/METADATA
hive_udf-1.1.4.dist-info/RECORD
