Metadata-Version: 2.1
Name: hive_udf
Version: 1.1.4
Summary: Hive UDF (user defined functions)
Author-email: Zepu Zhang <zepu.zhang@gmail.com>
Requires-Python: >=3.6
Classifier: Intended Audience :: Developers
Classifier: Programming Language :: Python :: 3
Classifier: Topic :: Software Development :: Libraries :: Python Modules
Requires-Dist: bandit ; extra == "test"
Requires-Dist: coverage[toml] ; extra == "test"
Requires-Dist: flake8 ; extra == "test"
Requires-Dist: mypy ; extra == "test"
Requires-Dist: numpy ; extra == "test"
Requires-Dist: pandas ; extra == "test"
Requires-Dist: pylint ; extra == "test"
Requires-Dist: pytest ; extra == "test"
Requires-Dist: pytest-asyncio ; extra == "test"
Project-URL: Source, https://github.com/zpz/hive-udf
Provides-Extra: test
